README.md
setup.py
codetest_lib.egg-info/PKG-INFO
codetest_lib.egg-info/SOURCES.txt
codetest_lib.egg-info/dependency_links.txt
codetest_lib.egg-info/requires.txt
codetest_lib.egg-info/top_level.txt
xes/AIspeak.py
xes/__init__.py
xes/common.py
xes/data.py
xes/ext.py
xes/garbage.py
xes/library.py
xes/map.py
xes/provinces.py
xes/sms.py
xes/timesecret.py
xes/weather.py
xes/word.py